uploads/__init__.py
uploads/session.py
igem_uploads-2.0.0.dist-info/LICENSE
igem_uploads-2.0.0.dist-info/METADATA
igem_uploads-2.0.0.dist-info/WHEEL
igem_uploads-2.0.0.dist-info/top_level.txt
igem_uploads-2.0.0.dist-info/RECORD
