Metadata-Version: 2.1
Name: igem-uploads
Version: 2.0.0
Summary: Helps iGEMers upload their files to the iGEM server.
Home-page: https://github.com/iGEM-HBUT-China/igem-uploads
Author: iGEM-HBUT-China
Author-email: liangtianyi2002@outlook.com
Classifier: Programming Language :: Python :: 3.8
Classifier: License :: OSI Approved
License-File: LICENSE
Requires-Dist: prettytable
Requires-Dist: requests
Requires-Dist: lxml
